{
  "project_info": {
    "project_number": "649683202154",
    "project_id": "chatapp-2fcb9",
    "storage_bucket": "chatapp-2fcb9.firebasestorage.app"
  },
  "client": [
    {
      "client_info": {
        "mobilesdk_app_id": "1:649683202154:android:4e0b675d11766c4c3fda13",
        "android_client_info": {
          "package_name": "com.example.iti_cu"
        }
      },
      "oauth_client": [],
      "api_key": [
        {
          "current_key": "AIzaSyC9nlGR84xjVPloIJrP_MMLEECdo61lAbc"
        }
      ],
      "services": {
        "appinvite_service": {
          "other_platform_oauth_client": []
        }
      }
    }
  ],
  "configuration_version": "1"
}